scripts/create_release.py
xplainable_client/__init__.py
xplainable_client/client/__init__.py
xplainable_client/client/autotrain.py
xplainable_client/client/base.py
xplainable_client/client/client.py
xplainable_client/client/collections.py
xplainable_client/client/datasets.py
xplainable_client/client/deployments.py
xplainable_client/client/gpt.py
xplainable_client/client/inference.py
xplainable_client/client/misc.py
xplainable_client/client/models.py
xplainable_client/client/preprocessing.py
xplainable_client/client/session.py
xplainable_client/client/py_models/__init__.py
xplainable_client/client/py_models/auth.py
xplainable_client/client/py_models/autotrain.py
xplainable_client/client/py_models/collections.py
xplainable_client/client/py_models/datasets.py
xplainable_client/client/py_models/deployments.py
xplainable_client/client/py_models/gpt.py
xplainable_client/client/py_models/inference.py
xplainable_client/client/py_models/misc.py
xplainable_client/client/py_models/models.py
xplainable_client/client/py_models/preprocessing.py
xplainable_client/client/utils/__init__.py
xplainable_client/client/utils/constants.py
xplainable_client/client/utils/helpers.py
xplainable_client/client/utils/mcp_markers.py
xplainable_client-1.3.1.post6.dist-info/licenses/LICENSE
xplainable_client-1.3.1.post6.dist-info/METADATA
xplainable_client-1.3.1.post6.dist-info/WHEEL
xplainable_client-1.3.1.post6.dist-info/top_level.txt
xplainable_client-1.3.1.post6.dist-info/RECORD
