Metadata-Version: 2.4
Name: xplainable-client
Version: 1.3.1.post6
Summary: The client for persisting and deploying models to Xplainable cloud.
Author-email: xplainable pty ltd <contact@xplainable.io>
License:                     GNU AFFERO GENERAL PUBLIC LICENSE
Classifier: Programming Language :: Python :: 3.10
Classifier: Programming Language :: Python :: 3.11
Classifier: Operating System :: OS Independent
Requires-Python: >=3.10
License-File: LICENSE
Requires-Dist: numpy>=2.0.0
Requires-Dist: pandas>=2.2.3
Requires-Dist: pyperclip
Requires-Dist: pydantic>=2.0.0
Requires-Dist: Requests
Requires-Dist: scikit_learn
Requires-Dist: setuptools>=65.5.1
Requires-Dist: urllib3
Requires-Dist: xplainable
Dynamic: license-file
